kaliroot_security_cli-2.3.1.dist-info/licenses/LICENSE
kalirootcli/__init__.py
kalirootcli/__main__.py
kalirootcli/agent.py
kalirootcli/ai_handler.py
kalirootcli/api_client.py
kalirootcli/auth.py
kalirootcli/chat_manager.py
kalirootcli/cli_wrapper.py
kalirootcli/config.py
kalirootcli/database_manager.py
kalirootcli/distro_detector.py
kalirootcli/main.py
kalirootcli/payments.py
kalirootcli/subscription.py
kalirootcli/web_search.py
kalirootcli/ui/__init__.py
kalirootcli/ui/colors.py
kalirootcli/ui/display.py
kalirootcli/ui/menus.py
kaliroot_security_cli-2.3.1.dist-info/METADATA
kaliroot_security_cli-2.3.1.dist-info/WHEEL
kaliroot_security_cli-2.3.1.dist-info/entry_points.txt
kaliroot_security_cli-2.3.1.dist-info/top_level.txt
kaliroot_security_cli-2.3.1.dist-info/RECORD
