Metadata-Version: 2.4
Name: kaliroot-security-cli
Version: 2.3.1
Summary: Professional Cybersecurity Agents & CLI Assistant
Author-email: KaliRootCode <kalirootcode@proton.me>
License: MIT
Project-URL: Homepage, https://github.com/kalirootcode/KaliRootCLI
Project-URL: Repository, https://github.com/kalirootcode/KaliRootCLI
Project-URL: Issues, https://github.com/kalirootcode/KaliRootCLI/issues
Keywords: cybersecurity,hacking,pentesting,kali,termux,cli,ai,agent
Classifier: Development Status :: 5 - Production/Stable
Classifier: Environment :: Console
Classifier: Intended Audience :: Developers
Classifier: Intended Audience :: Information Technology
Classifier: License :: OSI Approved :: MIT License
Classifier: Operating System :: POSIX :: Linux
Classifier: Operating System :: Android
Classifier: Programming Language :: Python :: 3
Classifier: Programming Language :: Python :: 3.8
Classifier: Programming Language :: Python :: 3.9
Classifier: Programming Language :: Python :: 3.10
Classifier: Programming Language :: Python :: 3.11
Classifier: Programming Language :: Python :: 3.12
Classifier: Topic :: Security
Classifier: Topic :: System :: Systems Administration
Requires-Python: >=3.8
License-File: LICENSE
Requires-Dist: requests>=2.31.0
Requires-Dist: rich>=13.0.0
Requires-Dist: python-dotenv>=1.0.0
Requires-Dist: tiktoken>=0.5.0
Dynamic: license-file
